{
    "plantData": [
        {
            "thePlantRow": 0,
            "thePlantColumn": 0,
            "thePlantType": 900,
            "growStage": 2,
            "waterLevel": 100,
            "love": 0,
            "nextTime": 1734177645,
            "needTool": 1
        },
        {
            "thePlantRow": 0,
            "thePlantColumn": 1,
            "thePlantType": 901,
            "growStage": 2,
            "waterLevel": 100,
            "love": 0,
            "nextTime": 1734177655,
            "needTool": 1
        },
        {
            "thePlantRow": 0,
            "thePlantColumn": 2,
            "thePlantType": 902,
            "growStage": 2,
            "waterLevel": 100,
            "love": 0,
            "nextTime": 1734177665,
            "needTool": 1
        },
        {
            "thePlantRow": 0,
            "thePlantColumn": 3,
            "thePlantType": 903,
            "growStage": 2,
            "waterLevel": 100,
            "love": 0,
            "nextTime": 1734177675,
            "needTool": 1
        },
        {
            "thePlantRow": 0,
            "thePlantColumn": 4,
            "thePlantType": 904,
            "growStage": 2,
            "waterLevel": 100,
            "love": 0,
            "nextTime": 1734177685,
            "needTool": 1
        },
        {
            "thePlantRow": 0,
            "thePlantColumn": 5,
            "thePlantType": 905,
            "growStage": 2,
            "waterLevel": 100,
            "love": 0,
            "nextTime": 1734177695,
            "needTool": 1
        },
        {
            "thePlantRow": 0,
            "thePlantColumn": 6,
            "thePlantType": 906,
            "growStage": 2,
            "waterLevel": 100,
            "love": 0,
            "nextTime": 1734177705,
            "needTool": 1
        },
        {
            "thePlantRow": 0,
            "thePlantColumn": 7,
            "thePlantType": 907,
            "growStage": 2,
            "waterLevel": 100,
            "love": 0,
            "nextTime": 1734177715,
            "needTool": 1
        },
        {
            "thePlantRow": 1,
            "thePlantColumn": 0,
            "thePlantType": 908,
            "growStage": 2,
            "waterLevel": 100,
            "love": 0,
            "nextTime": 1734177725,
            "needTool": 1
        },
        {
            "thePlantRow": 1,
            "thePlantColumn": 1,
            "thePlantType": 909,
            "growStage": 2,
            "waterLevel": 100,
            "love": 0,
            "nextTime": 1734177735,
            "needTool": 1
        },
        {
            "thePlantRow": 1,
            "thePlantColumn": 2,
            "thePlantType": 910,
            "growStage": 2,
            "waterLevel": 100,
            "love": 0,
            "nextTime": 1734177745,
            "needTool": 1
        },
        {
            "thePlantRow": 1,
            "thePlantColumn": 3,
            "thePlantType": 911,
            "growStage": 2,
            "waterLevel": 100,
            "love": 0,
            "nextTime": 1734177755,
            "needTool": 1
        },
        {
            "thePlantRow": 1,
            "thePlantColumn": 4,
            "thePlantType": 912,
            "growStage": 2,
            "waterLevel": 100,
            "love": 0,
            "nextTime": 1734177765,
            "needTool": 1
        },
        {
            "thePlantRow": 1,
            "thePlantColumn": 5,
            "thePlantType": 913,
            "growStage": 2,
            "waterLevel": 100,
            "love": 0,
            "nextTime": 1734177775,
            "needTool": 1
        },
        {
            "thePlantRow": 1,
            "thePlantColumn": 6,
            "thePlantType": 914,
            "growStage": 2,
            "waterLevel": 100,
            "love": 0,
            "nextTime": 1734177785,
            "needTool": 1
        },
        {
            "thePlantRow": 1,
            "thePlantColumn": 7,
            "thePlantType": 915,
            "growStage": 2,
            "waterLevel": 100,
            "love": 0,
            "nextTime": 1734177795,
            "needTool": 1
        },
        {
            "thePlantRow": 2,
            "thePlantColumn": 0,
            "thePlantType": 916,
            "growStage": 2,
            "waterLevel": 100,
            "love": 0,
            "nextTime": 1734177805,
            "needTool": 1
        },
        {
            "thePlantRow": 2,
            "thePlantColumn": 1,
            "thePlantType": 917,
            "growStage": 2,
            "waterLevel": 100,
            "love": 0,
            "nextTime": 1734177815,
            "needTool": 1
        },
        {
            "thePlantRow": 2,
            "thePlantColumn": 2,
            "thePlantType": 918,
            "growStage": 2,
            "waterLevel": 100,
            "love": 0,
            "nextTime": 1734177825,
            "needTool": 1
        },
        {
            "thePlantRow": 2,
            "thePlantColumn": 3,
            "thePlantType": 919,
            "growStage": 2,
            "waterLevel": 100,
            "love": 0,
            "nextTime": 1734177835,
            "needTool": 1
        },
        {
            "thePlantRow": 2,
            "thePlantColumn": 4,
            "thePlantType": 920,
            "growStage": 2,
            "waterLevel": 100,
            "love": 0,
            "nextTime": 1734177845,
            "needTool": 1
        },
        {
            "thePlantRow": 2,
            "thePlantColumn": 5,
            "thePlantType": 921,
            "growStage": 2,
            "waterLevel": 100,
            "love": 0,
            "nextTime": 1734177855,
            "needTool": 1
        },
        {
            "thePlantRow": 2,
            "thePlantColumn": 6,
            "thePlantType": 922,
            "growStage": 2,
            "waterLevel": 100,
            "love": 0,
            "nextTime": 1734177865,
            "needTool": 1
        },
        {
            "thePlantRow": 2,
            "thePlantColumn": 7,
            "thePlantType": 923,
            "growStage": 2,
            "waterLevel": 100,
            "love": 0,
            "nextTime": 1734177875,
            "needTool": 1
        },
        {
            "thePlantRow": 3,
            "thePlantColumn": 0,
            "thePlantType": 924,
            "growStage": 2,
            "waterLevel": 100,
            "love": 0,
            "nextTime": 1734177885,
            "needTool": 1
        },
        {
            "thePlantRow": 3,
            "thePlantColumn": 1,
            "thePlantType": 917,
            "growStage": 2,
            "waterLevel": 100,
            "love": 0,
            "nextTime": 1734177895,
            "needTool": 1
        },
        {
            "thePlantRow": 3,
            "thePlantColumn": 2,
            "thePlantType": 905,
            "growStage": 2,
            "waterLevel": 100,
            "love": 0,
            "nextTime": 1734177905,
            "needTool": 1
        },
        {
            "thePlantRow": 3,
            "thePlantColumn": 3,
            "thePlantType": 903,
            "growStage": 2,
            "waterLevel": 100,
            "love": 0,
            "nextTime": 1734177915,
            "needTool": 1
        },
        {
            "thePlantRow": 3,
            "thePlantColumn": 4,
            "thePlantType": 921,
            "growStage": 2,
            "waterLevel": 100,
            "love": 0,
            "nextTime": 1734177925,
            "needTool": 1
        },
        {
            "thePlantRow": 3,
            "thePlantColumn": 5,
            "thePlantType": 904,
            "growStage": 2,
            "waterLevel": 100,
            "love": 0,
            "nextTime": 1734177935,
            "needTool": 1
        },
        {
            "thePlantRow": 3,
            "thePlantColumn": 6,
            "thePlantType": 1033,
            "growStage": 2,
            "waterLevel": 100,
            "love": 0,
            "nextTime": 1734177945,
            "needTool": 1
        },
        {
            "thePlantRow": 3,
            "thePlantColumn": 7,
            "thePlantType": 1033,
            "growStage": 2,
            "waterLevel": 100,
            "love": 0,
            "nextTime": 1734177955,
            "needTool": 1
        }
    ]
}