{
    "plantData": [
        {
            "thePlantRow": 0,
            "thePlantColumn": 0,
            "thePlantType": 32,
            "growStage": 2,
            "waterLevel": 100,
            "love": 0,
            "nextTime": 1738294638,
            "needTool": 2,
            "page": 10
        },
        {
            "thePlantRow": 0,
            "thePlantColumn": 1,
            "thePlantType": 33,
            "growStage": 2,
            "waterLevel": 100,
            "love": 0,
            "nextTime": 1738294638,
            "needTool": 2,
            "page": 10
        },
        {
            "thePlantRow": 0,
            "thePlantColumn": 2,
            "thePlantType": 34,
            "growStage": 2,
            "waterLevel": 100,
            "love": 0,
            "nextTime": 1738294638,
            "needTool": 2,
            "page": 10
        },
        {
            "thePlantRow": 0,
            "thePlantColumn": 3,
            "thePlantType": 35,
            "growStage": 2,
            "waterLevel": 100,
            "love": 0,
            "nextTime": 1738294638,
            "needTool": 2,
            "page": 10
        },
        {
            "thePlantRow": 0,
            "thePlantColumn": 4,
            "thePlantType": 36,
            "growStage": 2,
            "waterLevel": 100,
            "love": 0,
            "nextTime": 1738294638,
            "needTool": 2,
            "page": 10
        },
        {
            "thePlantRow": 0,
            "thePlantColumn": 5,
            "thePlantType": 37,
            "growStage": 2,
            "waterLevel": 100,
            "love": 0,
            "nextTime": 1738294638,
            "needTool": 2,
            "page": 10
        },
        {
            "thePlantRow": 0,
            "thePlantColumn": 6,
            "thePlantType": 38,
            "growStage": 2,
            "waterLevel": 100,
            "love": 0,
            "nextTime": 1738294638,
            "needTool": 2,
            "page": 10
        },
        {
            "thePlantRow": 0,
            "thePlantColumn": 7,
            "thePlantType": 39,
            "growStage": 2,
            "waterLevel": 100,
            "love": 0,
            "nextTime": 1738294638,
            "needTool": 2,
            "page": 10
        },
        {
            "thePlantRow": 1,
            "thePlantColumn": 0,
            "thePlantType": 40,
            "growStage": 2,
            "waterLevel": 100,
            "love": 0,
            "nextTime": 1738294638,
            "needTool": 2,
            "page": 10
        },
        {
            "thePlantRow": 1,
            "thePlantColumn": 1,
            "thePlantType": 41,
            "growStage": 2,
            "waterLevel": 100,
            "love": 0,
            "nextTime": 1738294638,
            "needTool": 2,
            "page": 10
        },
        {
            "thePlantRow": 1,
            "thePlantColumn": 2,
            "thePlantType": 42,
            "growStage": 2,
            "waterLevel": 100,
            "love": 0,
            "nextTime": 1738294638,
            "needTool": 2,
            "page": 10
        },
        {
            "thePlantRow": 1,
            "thePlantColumn": 3,
            "thePlantType": 43,
            "growStage": 2,
            "waterLevel": 100,
            "love": 0,
            "nextTime": 1738294638,
            "needTool": 2,
            "page": 10
        },
        {
            "thePlantRow": 1,
            "thePlantColumn": 4,
            "thePlantType": 44,
            "growStage": 2,
            "waterLevel": 100,
            "love": 0,
            "nextTime": 1738294638,
            "needTool": 2,
            "page": 10
        },
        {
            "thePlantRow": 1,
            "thePlantColumn": 5,
            "thePlantType": 45,
            "growStage": 2,
            "waterLevel": 100,
            "love": 0,
            "nextTime": 1738294638,
            "needTool": 2,
            "page": 10
        },
        {
            "thePlantRow": 1,
            "thePlantColumn": 6,
            "thePlantType": 46,
            "growStage": 2,
            "waterLevel": 100,
            "love": 0,
            "nextTime": 1738294638,
            "needTool": 2,
            "page": 10
        },
        {
            "thePlantRow": 1,
            "thePlantColumn": 7,
            "thePlantType": 47,
            "growStage": 2,
            "waterLevel": 100,
            "love": 0,
            "nextTime": 1738294638,
            "needTool": 2,
            "page": 10
        },
        {
            "thePlantRow": 2,
            "thePlantColumn": 0,
            "thePlantType": 48,
            "growStage": 2,
            "waterLevel": 100,
            "love": 0,
            "nextTime": 1738294638,
            "needTool": 2,
            "page": 10
        },
        {
            "thePlantRow": 2,
            "thePlantColumn": 1,
            "thePlantType": 49,
            "growStage": 2,
            "waterLevel": 100,
            "love": 0,
            "nextTime": 1738294638,
            "needTool": 2,
            "page": 10
        },
        {
            "thePlantRow": 2,
            "thePlantColumn": 2,
            "thePlantType": 50,
            "growStage": 2,
            "waterLevel": 100,
            "love": 0,
            "nextTime": 1738294638,
            "needTool": 2,
            "page": 10
        },
        {
            "thePlantRow": 2,
            "thePlantColumn": 3,
            "thePlantType": 51,
            "growStage": 2,
            "waterLevel": 100,
            "love": 0,
            "nextTime": 1738294638,
            "needTool": 2,
            "page": 10
        },
        {
            "thePlantRow": 2,
            "thePlantColumn": 4,
            "thePlantType": 52,
            "growStage": 2,
            "waterLevel": 100,
            "love": 0,
            "nextTime": 1738294638,
            "needTool": 2,
            "page": 10
        },
        {
            "thePlantRow": 2,
            "thePlantColumn": 5,
            "thePlantType": 53,
            "growStage": 2,
            "waterLevel": 100,
            "love": 0,
            "nextTime": 1738294638,
            "needTool": 2,
            "page": 10
        },
        {
            "thePlantRow": 2,
            "thePlantColumn": 6,
            "thePlantType": 54,
            "growStage": 2,
            "waterLevel": 100,
            "love": 0,
            "nextTime": 1738294638,
            "needTool": 2,
            "page": 10
        },
        {
            "thePlantRow": 2,
            "thePlantColumn": 7,
            "thePlantType": 55,
            "growStage": 2,
            "waterLevel": 100,
            "love": 0,
            "nextTime": 1738294638,
            "needTool": 2,
            "page": 10
        },
        {
            "thePlantRow": 3,
            "thePlantColumn": 0,
            "thePlantType": 56,
            "growStage": 2,
            "waterLevel": 100,
            "love": 0,
            "nextTime": 1738294638,
            "needTool": 2,
            "page": 10
        },
        {
            "thePlantRow": 3,
            "thePlantColumn": 1,
            "thePlantType": 57,
            "growStage": 2,
            "waterLevel": 100,
            "love": 0,
            "nextTime": 1738294638,
            "needTool": 2,
            "page": 10
        },
        {
            "thePlantRow": 3,
            "thePlantColumn": 2,
            "thePlantType": 58,
            "growStage": 2,
            "waterLevel": 100,
            "love": 0,
            "nextTime": 1738294638,
            "needTool": 2,
            "page": 10
        },
        {
            "thePlantRow": 3,
            "thePlantColumn": 3,
            "thePlantType": 59,
            "growStage": 2,
            "waterLevel": 100,
            "love": 0,
            "nextTime": 1738294638,
            "needTool": 2,
            "page": 10
        },
        {
            "thePlantRow": 3,
            "thePlantColumn": 4,
            "thePlantType": 60,
            "growStage": 2,
            "waterLevel": 100,
            "love": 0,
            "nextTime": 1738294638,
            "needTool": 2,
            "page": 10
        },
        {
            "thePlantRow": 3,
            "thePlantColumn": 5,
            "thePlantType": 61,
            "growStage": 2,
            "waterLevel": 100,
            "love": 0,
            "nextTime": 1738294638,
            "needTool": 2,
            "page": 10
        },
        {
            "thePlantRow": 3,
            "thePlantColumn": 6,
            "thePlantType": 62,
            "growStage": 2,
            "waterLevel": 100,
            "love": 0,
            "nextTime": 1738294638,
            "needTool": 2,
            "page": 10
        },
        {
            "thePlantRow": 3,
            "thePlantColumn": 7,
            "thePlantType": 63,
            "growStage": 2,
            "waterLevel": 100,
            "love": 0,
            "nextTime": 1738294638,
            "needTool": 2,
            "page": 10
        }
    ]
}